wikiraces/__init__.py
wikiraces/cli.py
wikiraces/embed.py
wikiraces/rerank.py
wikiraces-0.1.1.dist-info/LICENSE
wikiraces-0.1.1.dist-info/METADATA
wikiraces-0.1.1.dist-info/WHEEL
wikiraces-0.1.1.dist-info/entry_points.txt
wikiraces-0.1.1.dist-info/RECORD
