Metadata-Version: 2.3
Name: wikiraces
Version: 0.1.1
Summary: AI-powered Wikipedia navigation using semantic similarity
License: MIT
Keywords: wikipedia,ai,semantic-search,nlp,navigation
Author: Mark Shteyn
Author-email: markshteyn@gmail.com
Requires-Python: >=3.9
Classifier: Development Status :: 4 - Beta
Classifier: Intended Audience :: Developers
Classifier: License :: OSI Approved :: MIT License
Classifier: Programming Language :: Python :: 3
Classifier: Programming Language :: Python :: 3.9
Classifier: Programming Language :: Python :: 3.10
Classifier: Programming Language :: Python :: 3.11
Classifier: Programming Language :: Python :: 3.12
Classifier: Programming Language :: Python :: 3.13
Classifier: Topic :: Scientific/Engineering :: Artificial Intelligence
Classifier: Topic :: Text Processing :: Linguistic
Requires-Dist: numpy (>=2.3.1,<3.0.0)
Requires-Dist: requests (>=2.32.4,<3.0.0)
Requires-Dist: sentence-transformers (>=5.0.0,<6.0.0)
Requires-Dist: tqdm (>=4.67.1,<5.0.0)
Requires-Dist: wikipedia (>=1.4.0,<2.0.0)
Project-URL: Homepage, https://github.com/markshteyn/wikiraces
Project-URL: Issues, https://github.com/markshteyn/wikiraces/issues
Project-URL: Repository, https://github.com/markshteyn/wikiraces
